{
  "bar": "community",
  "biergarten": "community",
  "cafe": "community",
  "fast_food": "community",
  "food_court": "community",
  "ice_cream": "community",
  "pub": "community",
  "restaurant": "community",
  "college": "academic",
  "driving_school": "academic",
  "kindergarten": "academic",
  "language_school": "academic",
  "library": "academic",
  "toy_library": "academic",
  "research_institute": "academic",
  "training": "academic",
  "music_school": "academic",
  "school": "academic",
  "traffic_park": "academic",
  "university": "academic",
  "bicycle_parking": "community",
  "bicycle_repair_station": "community",
  "bicycle_rental": "community",
  "boat_rental": "community",
  "boat_sharing": "community",
  "bus_station": "community",
  "car_rental": "community",
  "car_sharing": "community",
  "car_wash": "community",
  "compressed_air": "community",
  "vehicle_inspection": "community",
  "charging_station": "community",
  "driver_training": "community",
  "ferry_terminal": "community",
  "fuel": "community",
  "grit_bin": "community",
  "motorcycle_parking": "community",
  "parking": "community",
  "parking_entrance": "community",
  "parking_space": "community",
  "taxi": "community",
  "atm": "community",
  "bank": "community",
  "bureau_de_change": "community",
  "baby_hatch": "community",
  "clinic": "health-warnings",
  "dentist": "health-warnings",
  "doctors": "health-warnings",
  "hospital": "health-warnings",
  "nursing_home": "health-warnings",
  "pharmacy": "health-warnings",
  "social_facility": "health-warnings",
  "veterinary": "health-warnings",
  "arts_centre": "performing-arts",
  "brothel": "community",
  "casino": "community",
  "cinema": "performing-arts",
  "community_centre": "community",
  "conference_centre": "conferences",
  "events_venue": "community",
  "exhibition_centre": "expos",
  "fountain": "community",
  "gambling": "community",
  "love_hotel": "community",
  "music_venue": "concerts",
  "nightclub": "community",
  "planetarium": "community",
  "public_bookcase": "community",
  "social_centre": "community",
  "stripclub": "community",
  "studio": "performing-arts",
  "swingerclub": "community",
  "theatre": "performing-arts",
  "courthouse": "politics",
  "fire_station": "community",
  "police": "community",
  "post_box": "community",
  "post_depot": "community",
  "post_office": "community",
  "prison": "community",
  "ranger_station": "community",
  "townhall": "politics",
  "bbq": "community",
  "bench": "community",
  "dog_toilet": "community",
  "dressing_room": "community",
  "drinking_water": "community",
  "give_box": "community",
  "mailroom": "community",
  "parcel_locker": "community",
  "shelter": "community",
  "shower": "community",
  "telephone": "community",
  "toilets": "community",
  "water_point": "community",
  "watering_place": "community",
  "sanitary_dump_station": "community",
  "recycling": "community",
  "waste_basket": "community",
  "waste_disposal": "community",
  "waste_transfer_station": "community",
  "animal_boarding": "community",
  "animal_breeding": "community",
  "animal_shelter": "community",
  "animal_training": "community",
  "baking_oven": "community",
  "childcare": "community",
  "clock": "community",
  "crematorium": "community",
  "dive_centre": "community",
  "funeral_hall": "community",
  "grave_yard": "community",
  "hunting_stand": "community",
  "internet_cafe": "community",
  "kitchen": "community",
  "kneipp_water_cure": "community",
  "lounger": "community",
  "marketplace": "community",
  "monastery": "community",
  "photo_booth": "community",
  "place_of_mourning": "community",
  "place_of_worship": "community",
  "public_bath": "community",
  "public_building": "community",
  "refugee_site": "community",
  "vending_machine": "community",
  "user defined": "community"
}